LICENSE
MANIFEST.in
NOTICE
README.md
install.json
package.json
pyproject.toml
setup.py
tsconfig.json
tsconfig.test.json
amazon_codewhisperer_jupyterlab_ext/__init__.py
amazon_codewhisperer_jupyterlab_ext/constants.py
amazon_codewhisperer_jupyterlab_ext/handlers.py
amazon_codewhisperer_jupyterlab_ext/utils.py
amazon_codewhisperer_jupyterlab_ext.egg-info/PKG-INFO
amazon_codewhisperer_jupyterlab_ext.egg-info/SOURCES.txt
amazon_codewhisperer_jupyterlab_ext.egg-info/dependency_links.txt
amazon_codewhisperer_jupyterlab_ext.egg-info/not-zip-safe
amazon_codewhisperer_jupyterlab_ext.egg-info/requires.txt
amazon_codewhisperer_jupyterlab_ext.egg-info/top_level.txt
amazon_codewhisperer_jupyterlab_ext/auth/__init__.py
amazon_codewhisperer_jupyterlab_ext/auth/sso_auth_manager.py
amazon_codewhisperer_jupyterlab_ext/client/__init__.py
amazon_codewhisperer_jupyterlab_ext/client/codewhisperer/__init__.py
amazon_codewhisperer_jupyterlab_ext/client/codewhisperer/client_manager.py
amazon_codewhisperer_jupyterlab_ext/client/codewhisperer/iam_client_manager.py
amazon_codewhisperer_jupyterlab_ext/client/codewhisperer/sso_client_manager.py
amazon_codewhisperer_jupyterlab_ext/client/service_models/bearer/2022-11-11/service-2.json
amazon_codewhisperer_jupyterlab_ext/client/service_models/sigv4/2022-06-15/service-2.json
amazon_codewhisperer_jupyterlab_ext/client/service_models/telemetry/2017-07-25/service-2.json
amazon_codewhisperer_jupyterlab_ext/client/telemetry/__init__.py
amazon_codewhisperer_jupyterlab_ext/client/telemetry/telemetry.py
amazon_codewhisperer_jupyterlab_ext/env/__init__.py
amazon_codewhisperer_jupyterlab_ext/env/environment.py
amazon_codewhisperer_jupyterlab_ext/labextension/package.json
amazon_codewhisperer_jupyterlab_ext/labextension/schemas/amazon-codewhisperer-jupyterlab-ext/completer.json
amazon_codewhisperer_jupyterlab_ext/labextension/schemas/amazon-codewhisperer-jupyterlab-ext/package.json.orig
amazon_codewhisperer_jupyterlab_ext/labextension/static/571.2ac5bdb342624f52bccb.js
amazon_codewhisperer_jupyterlab_ext/labextension/static/706.e3114118781d2fad22ba.js
amazon_codewhisperer_jupyterlab_ext/labextension/static/706.e3114118781d2fad22ba.js.LICENSE.txt
amazon_codewhisperer_jupyterlab_ext/labextension/static/747.a6f42e6a863d7358a568.js
