Metadata-Version: 2.1
Name: amazon-codewhisperer-jupyterlab-ext
Version: 2.0.2
Summary: Amazon CodeWhisperer for JupyterLab
Home-page: https://aws.amazon.com/codewhisperer/
Author: Amazon CodeWhisperer
Author-email: codewhisperer@amazon.com
License: Apache 2.0
Keywords: Jupyter,JupyterLab,JupyterLab4,Amazon CodeWhisperer,CodeWhisperer,Code,Whisperer
Platform: Linux
Platform: Mac OS X
Platform: Windows
Classifier: License :: OSI Approved :: Apache Software License
Classifier: Programming Language :: Python
Classifier: Programming Language :: Python :: 3
Classifier: Programming Language :: Python :: 3.6
Classifier: Programming Language :: Python :: 3.7
Classifier: Programming Language :: Python :: 3.8
Classifier: Programming Language :: Python :: 3.9
Classifier: Framework :: Jupyter
Requires-Python: >=3.6
License-File: LICENSE
License-File: NOTICE
